indaleko_registry_service/__init__.py
indaleko_registry_service/cli.py
indaleko_registry_service/models.py
indaleko_registry_service/service.py
indaleko_registry_service-0.1.0.dist-info/licenses/LICENSE
indaleko_registry_service-0.1.0.dist-info/METADATA
indaleko_registry_service-0.1.0.dist-info/WHEEL
indaleko_registry_service-0.1.0.dist-info/top_level.txt
indaleko_registry_service-0.1.0.dist-info/RECORD
