Metadata-Version: 2.4
Name: indaleko-registry-service
Version: 0.1.0
Summary: Semantic registration service for UUID and metadata mapping.
Author-email: Tony Mason <fsgeek@cs.ubc.ca>
Requires-Python: >=3.12
License-File: LICENSE
Requires-Dist: fastapi
Requires-Dist: uvicorn[standard]
Requires-Dist: pydantic
Requires-Dist: twine>=6.1.0
Provides-Extra: dev
Requires-Dist: pytest; extra == "dev"
Requires-Dist: ruff; extra == "dev"
Requires-Dist: pytest-cov; extra == "dev"
Requires-Dist: httpx; extra == "dev"
Dynamic: license-file
